msastats.cpython-310-darwin.so
msastats-24.7.0.dist-info/RECORD
msastats-24.7.0.dist-info/WHEEL
msastats-24.7.0.dist-info/top_level.txt
msastats-24.7.0.dist-info/METADATA
