Metadata-Version: 2.1
Name: msastats
Version: 24.7.0
Summary: Simple utility to compute MSA summary statistics
Author: Elya Wygoda
Author-email: elya.wygoda@gmail.com
Requires-Python: >=3.7
Provides-Extra: test
Requires-Dist: pytest >=6.0 ; extra == 'test'
